aleksis_builddeps.py
aleksis_builddeps-2022.6.post1.dist-info/WHEEL
aleksis_builddeps-2022.6.post1.dist-info/METADATA
aleksis_builddeps-2022.6.post1.dist-info/RECORD
