Metadata-Version: 2.1
Name: aleksis-builddeps
Version: 2022.6.post1
Summary: AlekSIS (School Information System) — Build/Dev dependencies for apps
Home-page: https://aleksis.org/
License: EUPL-1.2-or-later
Keywords: SIS,education,school,digitisation,school apps
Author: Dominik George
Author-email: dominik.george@teckids.org
Maintainer: Jonathan Weth
Maintainer-email: wethjo@katharineum.de
Requires-Python: >=3.9,<4.0
Classifier: Development Status :: 3 - Alpha
Classifier: Framework :: Django :: 3.0
Classifier: Intended Audience :: Developers
Classifier: License :: Other/Proprietary License
Classifier: Programming Language :: Python :: 3
Classifier: Programming Language :: Python :: 3.10
Classifier: Programming Language :: Python :: 3.9
Requires-Dist: black (>=21.0)
Requires-Dist: curlylint (>=0.13.0,<0.14.0)
Requires-Dist: django-stubs (>=1.1,<2.0)
Requires-Dist: flake8 (>=4.0.0,<5.0.0)
Requires-Dist: flake8-bandit (>=3.0.0,<4.0.0)
Requires-Dist: flake8-black (>=0.3.0,<0.4.0)
Requires-Dist: flake8-builtins (>=1.4.1,<2.0.0)
Requires-Dist: flake8-django (>=1.0.0,<2.0.0)
Requires-Dist: flake8-docstrings (>=1.5.0,<2.0.0)
Requires-Dist: flake8-fixme (>=1.1.1,<2.0.0)
Requires-Dist: flake8-isort (>=4.0.0,<5.0.0)
Requires-Dist: flake8-mypy (>=17.8.0,<18.0.0)
Requires-Dist: flake8-rst-docstrings (>=0.2.0,<0.3.0)
Requires-Dist: freezegun (>=1.1.0,<2.0.0)
Requires-Dist: isort (>=5.0.0,<6.0.0)
Requires-Dist: pytest (>=6.0,<7.0)
Requires-Dist: pytest-cov (>=3.0.0,<4.0.0)
Requires-Dist: pytest-django (>=4.1,<5.0)
Requires-Dist: pytest-django-testing-postgresql (>=0.2,<0.3)
Requires-Dist: pytest-sugar (>=0.9.2,<0.10.0)
Requires-Dist: safety (>=1.8.5,<2.0.0)
Requires-Dist: selenium (>=4.0.0,<5.0.0)
Requires-Dist: sphinx (>=5.0,<6.0)
Requires-Dist: sphinx-autodoc-typehints (>=1.7,<2.0)
Requires-Dist: sphinx_material (>=0.0.35,<0.0.36)
Requires-Dist: sphinxcontrib-django (>=0.5.0,<0.6.0)
Requires-Dist: sphinxcontrib-svg2pdfconverter (>=1.1.1,<2.0.0)
Project-URL: Repository, https://edugit.org/AlekSIS/official/AlekSIS
